{
    "A": {
        "duration": 151.9600000000005,
        "intervals": [
            [
                486.643,
                489.13899999999995
            ],
            [
                500.334,
                502.94
            ],
            [
                522.863,
                527.2660000000001
            ],
            [
                530.592,
                534.465
            ],
            [
                555.415,
                559.809
            ],
            [
                577.392,
                587.542
            ],
            [
                593.705,
                600.5200000000001
            ],
            [
                602.124,
                612.606
            ],
            [
                706.372,
                707.411
            ],
            [
                716.423,
                717.155
            ],
            [
                719.078,
                722.973
            ],
            [
                741.631,
                751.801
            ],
            [
                1455.172,
                1460.592
            ],
            [
                1474.806,
                1478.277
            ],
            [
                1480.385,
                1482.955
            ],
            [
                1488.829,
                1502.398
            ],
            [
                1507.859,
                1515.3700000000001
            ],
            [
                1517.255,
                1522.5400000000002
            ],
            [
                1526.61,
                1533.464
            ],
            [
                1544.606,
                1551.192
            ],
            [
                1553.092,
                1569.645
            ],
            [
                1570.995,
                1573.818
            ],
            [
                1581.431,
                1585.4270000000001
            ],
            [
                2023.218,
                2027.7930000000001
            ],
            [
                2128.236,
                2136.086
            ],
            [
                2174.791,
                2175.626
            ],
            [
                2188.061,
                2188.621
            ],
            [
                2425.785,
                2426.455
            ],
            [
                2503.818,
                2504.8050000000003
            ],
            [
                2507.839,
                2508.629
            ]
        ]
    },
    "B": {
        "duration": 108.68400000000054,
        "intervals": [
            [
                279.803,
                280.578
            ],
            [
                1613.626,
                1631.773
            ],
            [
                1634.091,
                1676.4060000000002
            ],
            [
                1680.85,
                1700.8700000000001
            ],
            [
                1703.643,
                1731.0700000000002
            ]
        ]
    },
    "C": {
        "duration": 322.82000000000085,
        "intervals": [
            [
                147.812,
                252.042
            ],
            [
                281.779,
                329.99
            ],
            [
                1631.774,
                1634.091
            ],
            [
                1789.531,
                1864.442
            ],
            [
                2282.923,
                2338.4370000000004
            ],
            [
                2347.908,
                2366.609
            ],
            [
                2367.502,
                2386.438
            ]
        ]
    },
    "D": {
        "duration": 416.32999999999873,
        "intervals": [
            [
                0.314,
                0.317
            ],
            [
                4.011,
                4.0680000000000005
            ],
            [
                7.847,
                47.806999999999995
            ],
            [
                49.319,
                102.47999999999999
            ],
            [
                106.633,
                113.661
            ],
            [
                122.918,
                127.43400000000001
            ],
            [
                132.879,
                141.28699999999998
            ],
            [
                259.406,
                262.766
            ],
            [
                273.299,
                273.67499999999995
            ],
            [
                335.836,
                341.725
            ],
            [
                346.749,
                347.432
            ],
            [
                350.868,
                352.74399999999997
            ],
            [
                357.166,
                361.36499999999995
            ],
            [
                573.063,
                577.391
            ],
            [
                635.86,
                636.297
            ],
            [
                640.2,
                642.239
            ],
            [
                654.293,
                655.793
            ],
            [
                659.112,
                662.153
            ],
            [
                665.884,
                669.702
            ],
            [
                670.972,
                672.725
            ],
            [
                674.828,
                681.861
            ],
            [
                684.408,
                685.837
            ],
            [
                698.9,
                698.932
            ],
            [
                762.38,
                763.084
            ],
            [
                768.211,
                775.0110000000001
            ],
            [
                775.886,
                776.581
            ],
            [
                783.79,
                787.449
            ],
            [
                790.584,
                806.837
            ],
            [
                817.808,
                827.476
            ],
            [
                1010.313,
                1012.547
            ],
            [
                1023.231,
                1023.496
            ],
            [
                1051.031,
                1054.9579999999999
            ],
            [
                1253.21,
                1254.366
            ],
            [
                1261.973,
                1269.228
            ],
            [
                1273.868,
                1286.992
            ],
            [
                1589.936,
                1596.433
            ],
            [
                1598.41,
                1599.6080000000002
            ],
            [
                1605.191,
                1605.255
            ],
            [
                1607.941,
                1608.874
            ],
            [
                1611.492,
                1612.243
            ],
            [
                1679.495,
                1680.2749999999999
            ],
            [
                1738.896,
                1739.443
            ],
            [
                1742.923,
                1746.674
            ],
            [
                1754.303,
                1755.14
            ],
            [
                1757.627,
                1762.524
            ],
            [
                1764.988,
                1765.373
            ],
            [
                1769.236,
                1775.336
            ],
            [
                1777.95,
                1780.289
            ],
            [
                1892.813,
                1896.865
            ],
            [
                1927.611,
                1930.412
            ],
            [
                1999.402,
                2001.4080000000001
            ],
            [
                2042.891,
                2043.6660000000002
            ],
            [
                2082.122,
                2082.1299999999997
            ],
            [
                2090.203,
                2092.938
            ],
            [
                2095.396,
                2102.835
            ],
            [
                2104.611,
                2105.941
            ],
            [
                2114.851,
                2115.308
            ],
            [
                2193.961,
                2198.959
            ],
            [
                2205.333,
                2205.762
            ],
            [
                2209.481,
                2218.192
            ],
            [
                2223.472,
                2226.842
            ],
            [
                2230.354,
                2232.173
            ],
            [
                2235.283,
                2239.191
            ],
            [
                2239.52,
                2241.651
            ],
            [
                2243.822,
                2246.409
            ],
            [
                2247.418,
                2253.242
            ],
            [
                2258.467,
                2265.192
            ],
            [
                2269.666,
                2277.735
            ],
            [
                2346.611,
                2347.9089999999997
            ],
            [
                2403.986,
                2406.161
            ],
            [
                2406.537,
                2416.828
            ],
            [
                2417.565,
                2425.2149999999997
            ],
            [
                2430.668,
                2463.109
            ],
            [
                2468.391,
                2470.659
            ],
            [
                2473.48,
                2502.817
            ],
            [
                2505.003,
                2506.9570000000003
            ],
            [
                2512.659,
                2521.656
            ]
        ]
    },
    "E": {
        "duration": 369.9669999999997,
        "intervals": [
            [
                49.24,
                49.319
            ],
            [
                102.743,
                106.309
            ],
            [
                114.026,
                122.917
            ],
            [
                127.435,
                132.879
            ],
            [
                252.578,
                259.406
            ],
            [
                262.766,
                273.119
            ],
            [
                273.675,
                277.13300000000004
            ],
            [
                330.478,
                335.641
            ],
            [
                341.726,
                346.401
            ],
            [
                347.433,
                350.352
            ],
            [
                353.185,
                356.248
            ],
            [
                361.679,
                366.238
            ],
            [
                474.974,
                481.077
            ],
            [
                559.81,
                573.063
            ],
            [
                617.591,
                635.543
            ],
            [
                636.297,
                640.2
            ],
            [
                642.426,
                654.021
            ],
            [
                655.989,
                658.865
            ],
            [
                662.715,
                665.594
            ],
            [
                669.701,
                670.523
            ],
            [
                672.725,
                674.6030000000001
            ],
            [
                681.861,
                684.408
            ],
            [
                686.097,
                693.7520000000001
            ],
            [
                752.038,
                762.099
            ],
            [
                763.337,
                768.21
            ],
            [
                775.317,
                775.886
            ],
            [
                776.864,
                783.503
            ],
            [
                787.448,
                790.295
            ],
            [
                806.838,
                817.572
            ],
            [
                1017.038,
                1022.841
            ],
            [
                1023.496,
                1049.875
            ],
            [
                1055.241,
                1056.355
            ],
            [
                1250.716,
                1253.2099999999998
            ],
            [
                1254.611,
                1261.973
            ],
            [
                1269.228,
                1273.499
            ],
            [
                1444.279,
                1449.321
            ],
            [
                1579.25,
                1581.43
            ],
            [
                1585.427,
                1589.5059999999999
            ],
            [
                1596.432,
                1598.1200000000001
            ],
            [
                1599.608,
                1605.19
            ],
            [
                1605.52,
                1607.604
            ],
            [
                1608.874,
                1611.064
            ],
            [
                1676.811,
                1679.27
            ],
            [
                1731.368,
                1738.896
            ],
            [
                1739.921,
                1742.5910000000001
            ],
            [
                1747.005,
                1750.906
            ],
            [
                1755.368,
                1757.336
            ],
            [
                1762.923,
                1763.881
            ],
            [
                1765.55,
                1769.236
            ],
            [
                1775.733,
                1777.9499999999998
            ],
            [
                1781.18,
                1783.286
            ],
            [
                1864.73,
                1871.346
            ],
            [
                1991.593,
                1999.19
            ],
            [
                2004.612,
                2005.731
            ],
            [
                2027.793,
                2042.562
            ],
            [
                2086.027,
                2090.204
            ],
            [
                2093.293,
                2095.1440000000002
            ],
            [
                2103.04,
                2104.371
            ],
            [
                2105.941,
                2114.4289999999996
            ],
            [
                2191.516,
                2193.9610000000002
            ],
            [
                2199.221,
                2204.825
            ],
            [
                2206.045,
                2209.109
            ],
            [
                2218.192,
                2223.1020000000003
            ],
            [
                2227.274,
                2230.354
            ],
            [
                2232.561,
                2234.871
            ],
            [
                2239.463,
                2239.52
            ],
            [
                2241.896,
                2243.4
            ],
            [
                2246.635,
                2247.418
            ],
            [
                2253.243,
                2258.069
            ],
            [
                2265.192,
                2269.365
            ],
            [
                2339.116,
                2346.257
            ],
            [
                2389.049,
                2403.5429999999997
            ],
            [
                2406.517,
                2406.537
            ],
            [
                2416.827,
                2417.2290000000003
            ],
            [
                2427.005,
                2428.9790000000003
            ],
            [
                2465.103,
                2468.39
            ]
        ]
    },
    "F": {
        "duration": 175.35999999999945,
        "intervals": [
            [
                0.317,
                3.498
            ],
            [
                4.069,
                7.539
            ],
            [
                439.967,
                441.63399999999996
            ],
            [
                489.139,
                499.988
            ],
            [
                502.939,
                522.489
            ],
            [
                527.266,
                530.592
            ],
            [
                534.465,
                555.4159999999999
            ],
            [
                587.542,
                593.705
            ],
            [
                600.77,
                602.1229999999999
            ],
            [
                612.895,
                617.591
            ],
            [
                698.932,
                706.122
            ],
            [
                707.412,
                716.1700000000001
            ],
            [
                717.155,
                718.875
            ],
            [
                723.224,
                741.442
            ],
            [
                1460.968,
                1474.806
            ],
            [
                1478.277,
                1479.983
            ],
            [
                1483.291,
                1488.829
            ],
            [
                1502.398,
                1507.859
            ],
            [
                1515.37,
                1516.9089999999999
            ],
            [
                1522.785,
                1526.2730000000001
            ],
            [
                1533.463,
                1544.606
            ],
            [
                1551.192,
                1552.834
            ],
            [
                1569.829,
                1570.774
            ],
            [
                1573.818,
                1578.96
            ],
            [
                1751.487,
                1754.303
            ],
            [
                1921.204,
                1923.5629999999999
            ],
            [
                1939.032,
                1941.2649999999999
            ],
            [
                2001.409,
                2003.3139999999999
            ],
            [
                2116.23,
                2116.993
            ],
            [
                2176.077,
                2176.391
            ],
            [
                2471.676,
                2472.491
            ],
            [
                2509.583,
                2512.204
            ]
        ]
    },
    "G": {
        "duration": 299.52199999999857,
        "intervals": [
            [
                833.291,
                1010.023
            ],
            [
                1012.547,
                1016.442
            ],
            [
                1060.302,
                1061.2469999999998
            ],
            [
                1680.818,
                1680.85
            ],
            [
                2005.73,
                2023.2179999999998
            ],
            [
                2048.147,
                2081.727
            ],
            [
                2082.13,
                2086.0269999999996
            ],
            [
                2116.992,
                2127.9930000000004
            ],
            [
                2136.387,
                2174.535
            ],
            [
                2176.637,
                2187.908
            ],
            [
                2188.622,
                2191.0809999999997
            ],
            [
                2366.609,
                2366.683
            ]
        ]
    },
    "H": {
        "duration": 190.76,
        "intervals": [
            [
                1061.905,
                1250.358
            ],
            [
                1701.336,
                1703.643
            ]
        ]
    },
    "I": {
        "duration": 363.2439999999999,
        "intervals": [
            [
                369.809,
                439.506
            ],
            [
                441.634,
                474.434
            ],
            [
                828.205,
                828.499
            ],
            [
                1291.462,
                1444.279
            ],
            [
                1871.346,
                1892.813
            ],
            [
                1897.253,
                1920.927
            ],
            [
                1923.563,
                1927.6109999999999
            ],
            [
                1930.694,
                1938.814
            ],
            [
                1941.265,
                1991.592
            ]
        ]
    }
}