{
    "A": {
        "duration": 152.7170000000006,
        "intervals": [
            [
                3.389,
                3.671
            ],
            [
                796.007,
                801.262
            ],
            [
                807.811,
                814.104
            ],
            [
                823.414,
                825.01
            ],
            [
                830.459,
                835.2009999999999
            ],
            [
                841.328,
                844.355
            ],
            [
                901.592,
                902.848
            ],
            [
                910.668,
                916.933
            ],
            [
                926.78,
                928.908
            ],
            [
                934.202,
                936.404
            ],
            [
                947.05,
                948.5569999999999
            ],
            [
                950.039,
                955.263
            ],
            [
                959.968,
                960.793
            ],
            [
                967.081,
                968.876
            ],
            [
                971.61,
                974.342
            ],
            [
                1264.319,
                1266.8709999999999
            ],
            [
                1278.474,
                1280.6319999999998
            ],
            [
                1281.879,
                1282.9689999999998
            ],
            [
                1330.952,
                1333.144
            ],
            [
                1504.789,
                1511.169
            ],
            [
                1526.148,
                1534.242
            ],
            [
                1544.371,
                1545.8860000000002
            ],
            [
                1551.008,
                1553.3110000000001
            ],
            [
                1558.646,
                1562.441
            ],
            [
                1568.732,
                1570.617
            ],
            [
                1572.394,
                1575.097
            ],
            [
                1581.365,
                1590.794
            ],
            [
                1596.738,
                1597.99
            ],
            [
                1599.549,
                1601.259
            ],
            [
                1609.502,
                1611.973
            ],
            [
                1615.24,
                1616.762
            ],
            [
                1620.501,
                1624.463
            ],
            [
                1626.99,
                1628.2
            ],
            [
                1629.403,
                1634.872
            ],
            [
                1638.046,
                1644.054
            ],
            [
                1647.498,
                1650.8780000000002
            ],
            [
                1663.784,
                1667.93
            ],
            [
                1930.8,
                1932.844
            ],
            [
                1938.592,
                1939.3090000000002
            ],
            [
                1955.04,
                1959.208
            ],
            [
                1962.811,
                1964.31
            ],
            [
                1973.128,
                1977.792
            ],
            [
                1982.993,
                1986.83
            ],
            [
                1987.696,
                1988.7269999999999
            ],
            [
                1992.153,
                2001.996
            ],
            [
                2004.279,
                2005.81
            ],
            [
                2026.86,
                2029.091
            ],
            [
                2034.02,
                2034.817
            ]
        ]
    },
    "B": {
        "duration": 173.21300000000014,
        "intervals": [
            [
                255.52,
                255.566
            ],
            [
                268.41,
                272.24600000000004
            ],
            [
                559.538,
                559.54
            ],
            [
                1114.412,
                1114.945
            ],
            [
                1612.173,
                1612.273
            ],
            [
                1839.21,
                1842.833
            ],
            [
                1862.457,
                1865.8370000000002
            ],
            [
                2096.903,
                2224.4089999999997
            ],
            [
                2265.756,
                2299.943
            ]
        ]
    },
    "C": {
        "duration": 371.66900000000027,
        "intervals": [
            [
                257.494,
                268.411
            ],
            [
                272.53,
                320.433
            ],
            [
                343.103,
                370.315
            ],
            [
                381.998,
                428.112
            ],
            [
                463.627,
                472.906
            ],
            [
                491.1,
                516.451
            ],
            [
                518.775,
                540.712
            ],
            [
                724.142,
                728.514
            ],
            [
                731.465,
                735.392
            ],
            [
                740.192,
                746.565
            ],
            [
                754.832,
                756.773
            ],
            [
                838.286,
                840.453
            ],
            [
                1692.519,
                1746.836
            ],
            [
                1801.442,
                1839.21
            ],
            [
                1842.833,
                1862.1499999999999
            ],
            [
                1865.989,
                1895.7050000000002
            ],
            [
                1927.611,
                1929.8180000000002
            ],
            [
                1934.7,
                1935.0710000000001
            ],
            [
                1941.967,
                1945.7910000000002
            ],
            [
                1977.792,
                1981.223
            ],
            [
                2422.594,
                2435.819
            ]
        ]
    },
    "D": {
        "duration": 402.9110000000004,
        "intervals": [
            [
                4.055,
                4.438
            ],
            [
                8.397,
                15.577
            ],
            [
                23.227,
                24.592
            ],
            [
                42.452,
                44.233999999999995
            ],
            [
                50.127,
                55.957
            ],
            [
                60.146,
                63.081
            ],
            [
                69.437,
                70.88799999999999
            ],
            [
                72.881,
                76.193
            ],
            [
                79.007,
                83.872
            ],
            [
                86.898,
                90.077
            ],
            [
                92.536,
                95.239
            ],
            [
                98.53,
                100.315
            ],
            [
                104.703,
                111.849
            ],
            [
                116.414,
                119.32300000000001
            ],
            [
                122.432,
                123.267
            ],
            [
                126.669,
                138.101
            ],
            [
                140.523,
                145.321
            ],
            [
                146.792,
                148.792
            ],
            [
                150.009,
                152.736
            ],
            [
                159.43,
                165.119
            ],
            [
                171.651,
                175.407
            ],
            [
                183.08,
                187.991
            ],
            [
                194.678,
                204.08800000000002
            ],
            [
                206.148,
                208.249
            ],
            [
                231.809,
                239.592
            ],
            [
                245.18,
                251.07500000000002
            ],
            [
                253.16,
                255.21699999999998
            ],
            [
                324.397,
                330.315
            ],
            [
                338.629,
                342.848
            ],
            [
                373.265,
                379.426
            ],
            [
                430.984,
                435.68699999999995
            ],
            [
                443.333,
                446.82800000000003
            ],
            [
                451.403,
                459.594
            ],
            [
                472.907,
                477.905
            ],
            [
                516.451,
                517.847
            ],
            [
                545.483,
                557.434
            ],
            [
                660.299,
                661.814
            ],
            [
                667.347,
                675.9879999999999
            ],
            [
                719.663,
                720.819
            ],
            [
                761.093,
                770.752
            ],
            [
                774.017,
                787.0500000000001
            ],
            [
                790.682,
                792.283
            ],
            [
                804.2,
                805.3000000000001
            ],
            [
                853.6,
                854.155
            ],
            [
                857.859,
                860.259
            ],
            [
                862.058,
                865.593
            ],
            [
                869.122,
                870.592
            ],
            [
                872.708,
                874.7919999999999
            ],
            [
                879.815,
                880.394
            ],
            [
                888.006,
                891.3009999999999
            ],
            [
                894.875,
                897.5949999999999
            ],
            [
                899.385,
                900.494
            ],
            [
                986.421,
                993.029
            ],
            [
                1122.866,
                1125.2839999999999
            ],
            [
                1127.091,
                1132.599
            ],
            [
                1138.274,
                1138.3039999999999
            ],
            [
                1141.552,
                1145.194
            ],
            [
                1146.464,
                1150.19
            ],
            [
                1153.955,
                1154.492
            ],
            [
                1158.541,
                1160.191
            ],
            [
                1459.613,
                1466.023
            ],
            [
                1468.046,
                1475.6580000000001
            ],
            [
                1478.258,
                1480.896
            ],
            [
                1488.21,
                1492.055
            ],
            [
                1676.818,
                1678.668
            ],
            [
                1681.575,
                1691.137
            ],
            [
                1746.836,
                1749.2050000000002
            ],
            [
                1751.88,
                1757.622
            ],
            [
                1759.885,
                1760.45
            ],
            [
                1761.88,
                1771.7150000000001
            ],
            [
                1775.223,
                1780.192
            ],
            [
                1782.857,
                1787.433
            ],
            [
                1788.028,
                1800.165
            ],
            [
                1909.265,
                1911.3120000000001
            ],
            [
                1914.477,
                1916.814
            ],
            [
                1920.107,
                1924.5919999999999
            ],
            [
                2038.055,
                2049.977
            ],
            [
                2053.527,
                2057.703
            ],
            [
                2059.806,
                2060.407
            ],
            [
                2069.209,
                2071.0829999999996
            ],
            [
                2078.462,
                2081.737
            ],
            [
                2088.752,
                2090.936
            ],
            [
                2230.997,
                2236.673
            ],
            [
                2248.585,
                2250.401
            ],
            [
                2258.774,
                2260.99
            ],
            [
                2306.578,
                2313.8160000000003
            ],
            [
                2317.763,
                2321.278
            ],
            [
                2435.819,
                2452.4170000000004
            ],
            [
                2458.033,
                2459.304
            ],
            [
                2462.776,
                2463.1929999999998
            ],
            [
                2470.895,
                2473.109
            ],
            [
                2477.265,
                2480.5989999999997
            ],
            [
                2488.2,
                2494.009
            ],
            [
                2503.421,
                2507.84
            ],
            [
                2513.054,
                2516.6090000000004
            ]
        ]
    },
    "E": {
        "duration": 384.91200000000117,
        "intervals": [
            [
                4.836,
                8.397
            ],
            [
                16.266,
                22.851
            ],
            [
                24.592,
                42.453
            ],
            [
                45.158,
                49.522000000000006
            ],
            [
                56.246,
                59.883
            ],
            [
                63.44,
                68.278
            ],
            [
                71.547,
                72.88199999999999
            ],
            [
                76.192,
                77.66499999999999
            ],
            [
                83.872,
                86.616
            ],
            [
                90.31,
                92.536
            ],
            [
                95.767,
                98.53
            ],
            [
                100.555,
                104.39200000000001
            ],
            [
                112.295,
                116.414
            ],
            [
                119.607,
                122.431
            ],
            [
                123.755,
                124.95299999999999
            ],
            [
                138.48,
                139.93599999999998
            ],
            [
                145.805,
                146.792
            ],
            [
                148.994,
                150.008
            ],
            [
                153.887,
                159.42999999999998
            ],
            [
                165.9,
                171.651
            ],
            [
                175.854,
                183.08
            ],
            [
                188.354,
                194.678
            ],
            [
                204.088,
                205.6
            ],
            [
                209.01,
                231.809
            ],
            [
                239.591,
                244.48899999999998
            ],
            [
                251.357,
                252.528
            ],
            [
                330.315,
                338.356
            ],
            [
                379.748,
                381.997
            ],
            [
                435.687,
                443.333
            ],
            [
                446.828,
                450.911
            ],
            [
                477.905,
                491.099
            ],
            [
                661.814,
                667.347
            ],
            [
                720.819,
                721.626
            ],
            [
                757.134,
                760.779
            ],
            [
                770.968,
                773.637
            ],
            [
                787.355,
                790.206
            ],
            [
                792.283,
                793.169
            ],
            [
                860.517,
                862.0580000000001
            ],
            [
                865.895,
                868.425
            ],
            [
                870.591,
                872.192
            ],
            [
                874.792,
                878.708
            ],
            [
                880.394,
                888.006
            ],
            [
                891.3,
                894.3779999999999
            ],
            [
                897.595,
                899.198
            ],
            [
                978.964,
                986.421
            ],
            [
                993.217,
                993.9209999999999
            ],
            [
                1117.63,
                1122.546
            ],
            [
                1125.89,
                1127.092
            ],
            [
                1133.317,
                1137.226
            ],
            [
                1138.305,
                1141.2240000000002
            ],
            [
                1145.193,
                1145.988
            ],
            [
                1150.634,
                1153.391
            ],
            [
                1154.491,
                1158.542
            ],
            [
                1160.538,
                1173.83
            ],
            [
                1455.999,
                1459.614
            ],
            [
                1466.281,
                1467.791
            ],
            [
                1475.658,
                1478.0629999999999
            ],
            [
                1481.06,
                1488.052
            ],
            [
                1672.313,
                1676.4460000000001
            ],
            [
                1678.668,
                1681.1619999999998
            ],
            [
                1749.738,
                1751.8790000000001
            ],
            [
                1757.995,
                1759.5359999999998
            ],
            [
                1760.451,
                1761.573
            ],
            [
                1771.966,
                1775.223
            ],
            [
                1780.193,
                1781.192
            ],
            [
                1787.839,
                1788.028
            ],
            [
                1901.463,
                1909.264
            ],
            [
                1911.539,
                1914.477
            ],
            [
                1917.116,
                1920.106
            ],
            [
                1924.592,
                1925.7720000000002
            ],
            [
                2050.272,
                2053.527
            ],
            [
                2057.704,
                2059.626
            ],
            [
                2060.407,
                2068.726
            ],
            [
                2071.082,
                2078.2090000000003
            ],
            [
                2081.98,
                2088.752
            ],
            [
                2228.327,
                2230.9970000000003
            ],
            [
                2236.673,
                2248.302
            ],
            [
                2250.669,
                2258.429
            ],
            [
                2304.099,
                2306.578
            ],
            [
                2313.816,
                2317.763
            ],
            [
                2452.621,
                2458.033
            ],
            [
                2459.611,
                2462.5099999999998
            ],
            [
                2463.193,
                2470.683
            ],
            [
                2473.109,
                2477.2650000000003
            ],
            [
                2480.6,
                2487.8759999999997
            ],
            [
                2494.316,
                2503.26
            ],
            [
                2508.082,
                2513.053
            ],
            [
                2516.609,
                2521.653
            ]
        ]
    },
    "F": {
        "duration": 217.1180000000001,
        "intervals": [
            [
                256.397,
                256.591
            ],
            [
                371.922,
                372.346
            ],
            [
                657.3,
                657.4939999999999
            ],
            [
                717.758,
                718.4970000000001
            ],
            [
                801.262,
                803.849
            ],
            [
                805.758,
                807.2850000000001
            ],
            [
                814.104,
                822.6850000000001
            ],
            [
                825.01,
                829.895
            ],
            [
                835.512,
                838.286
            ],
            [
                845.049,
                853.5999999999999
            ],
            [
                855.536,
                856.2399999999999
            ],
            [
                902.848,
                910.3900000000001
            ],
            [
                916.934,
                925.924
            ],
            [
                930.354,
                934.202
            ],
            [
                936.919,
                946.725
            ],
            [
                955.263,
                959.5600000000001
            ],
            [
                960.793,
                967.081
            ],
            [
                969.03,
                970.466
            ],
            [
                975.473,
                978.9639999999999
            ],
            [
                993.921,
                994.081
            ],
            [
                1494.011,
                1494.269
            ],
            [
                1502.673,
                1504.435
            ],
            [
                1511.619,
                1524.896
            ],
            [
                1534.645,
                1543.7740000000001
            ],
            [
                1546.192,
                1549.844
            ],
            [
                1553.312,
                1557.397
            ],
            [
                1562.681,
                1568.732
            ],
            [
                1571.636,
                1572.394
            ],
            [
                1575.097,
                1581.095
            ],
            [
                1590.794,
                1595.9920000000002
            ],
            [
                1598.172,
                1599.549
            ],
            [
                1602.523,
                1609.502
            ],
            [
                1612.631,
                1615.24
            ],
            [
                1617.042,
                1619.639
            ],
            [
                1624.463,
                1626.4589999999998
            ],
            [
                1628.611,
                1629.402
            ],
            [
                1635.236,
                1638.046
            ],
            [
                1644.222,
                1647.498
            ],
            [
                1651.529,
                1663.034
            ],
            [
                1926.528,
                1927.289
            ],
            [
                1930.09,
                1930.8
            ],
            [
                1935.407,
                1938.592
            ],
            [
                1940.168,
                1941.56
            ],
            [
                1945.79,
                1954.888
            ],
            [
                1959.208,
                1960.97
            ],
            [
                1964.918,
                1972.262
            ],
            [
                1982.028,
                1982.993
            ],
            [
                1987.06,
                1987.696
            ],
            [
                1989.08,
                1991.864
            ],
            [
                2002.728,
                2004.279
            ],
            [
                2006.881,
                2025.9389999999999
            ],
            [
                2029.091,
                2034.02
            ],
            [
                2036.377,
                2038.0539999999999
            ],
            [
                2522.252,
                2522.392
            ]
        ]
    },
    "G": {
        "duration": 375.6669999999998,
        "intervals": [
            [
                559.54,
                645.852
            ],
            [
                648.305,
                656.3449999999999
            ],
            [
                659.44,
                659.99
            ],
            [
                676.716,
                715.331
            ],
            [
                728.774,
                731.466
            ],
            [
                735.392,
                739.72
            ],
            [
                746.565,
                749.7070000000001
            ],
            [
                752.073,
                753.712
            ],
            [
                994.783,
                1113.878
            ],
            [
                1275.487,
                1278.4740000000002
            ],
            [
                1304.227,
                1307.403
            ],
            [
                1899.41,
                1901.4640000000002
            ],
            [
                2322.5,
                2422.593
            ],
            [
                2537.143,
                2537.192
            ],
            [
                2547.793,
                2549.4700000000003
            ],
            [
                2552.524,
                2553.7419999999997
            ]
        ]
    },
    "H": {
        "duration": 331.9459999999997,
        "intervals": [
            [
                645.852,
                648.081
            ],
            [
                724.057,
                724.141
            ],
            [
                750.673,
                752.074
            ],
            [
                754.426,
                754.537
            ],
            [
                795.812,
                796.008
            ],
            [
                949.983,
                950.039
            ],
            [
                1116.823,
                1117.63
            ],
            [
                1175.285,
                1264.008
            ],
            [
                1267.112,
                1275.4869999999999
            ],
            [
                1280.946,
                1281.879
            ],
            [
                1283.21,
                1303.876
            ],
            [
                1307.402,
                1330.951
            ],
            [
                1333.316,
                1453.267
            ],
            [
                1496.163,
                1502.673
            ],
            [
                1933.694,
                1934.551
            ],
            [
                1961.879,
                1962.424
            ],
            [
                2264.585,
                2264.587
            ],
            [
                2523.353,
                2536.542
            ],
            [
                2537.192,
                2547.7929999999997
            ],
            [
                2550.248,
                2551.76
            ],
            [
                2554.62,
                2586.2690000000002
            ]
        ]
    }
}